lt_autosnap/__init__.py
lt_autosnap/autosnap.py
lt_autosnap/cli.py
lt_autosnap/config.py
lt_autosnap/errors.py
lt_autosnap/exit.py
lt_autosnap/logger.py
lt_autosnap/ltautosnap.conf
lt_autosnap/lvs.py
lt_autosnap/mounts.py
lt_autosnap/subproc.py
lt_autosnap/version.py
lt_autosnap-0.3.1.dist-info/entry_points.txt
lt_autosnap-0.3.1.dist-info/LICENSE.txt
lt_autosnap-0.3.1.dist-info/WHEEL
lt_autosnap-0.3.1.dist-info/METADATA
lt_autosnap-0.3.1.dist-info/RECORD
