Metadata-Version: 2.1
Name: lt-autosnap
Version: 0.3.1
Summary: LVM snapshot automation based on smbsnap from Samba.org
Home-page: https://gitlab.com/randallpittman/lt-autosnap
License: MIT
Author: Randall Pittman
Author-email: randall.pittman@oregonstate.edu
Requires-Python: >=3.6.8,<4.0.0
Classifier: Development Status :: 4 - Beta
Classifier: License :: OSI Approved :: MIT License
Classifier: Operating System :: POSIX :: Linux
Classifier: Programming Language :: Python :: 3
Classifier: Programming Language :: Python :: 3.10
Classifier: Programming Language :: Python :: 3.6
Classifier: Programming Language :: Python :: 3.7
Classifier: Programming Language :: Python :: 3.8
Classifier: Programming Language :: Python :: 3.9
Classifier: Topic :: System :: Operating System
Requires-Dist: dataclasses (>=0.8,<0.9); python_version >= "3.6" and python_version < "3.7"
Requires-Dist: single-version (>=1.5.1,<2.0.0)
Project-URL: Repository, https://gitlab.com/randallpittman/lt-autosnap
